tfConstrainedGauss/__init__.py
tfConstrainedGauss/helpers.py
tfConstrainedGauss/net_common.py
tfConstrainedGauss/solve_id/__init__.py
tfConstrainedGauss/solve_id/model_id.py
tfConstrainedGauss/solve_id/solve_id.py
tfConstrainedGauss/solve_me/__init__.py
tfConstrainedGauss/solve_me/model_me.py
tfConstrainedGauss/solve_me/solve_me.py
tfConstrainedGauss-0.1.0.dist-info/LICENSE
tfConstrainedGauss-0.1.0.dist-info/METADATA
tfConstrainedGauss-0.1.0.dist-info/WHEEL
tfConstrainedGauss-0.1.0.dist-info/top_level.txt
tfConstrainedGauss-0.1.0.dist-info/RECORD
