Metadata-Version: 2.1
Name: tfConstrainedGauss
Version: 0.1.0
Summary: TensorFlow package for estimating constrained precision matrices
Home-page: https://github.com/smrfeld/tf-constrained-gauss
Author: Oliver K. Ernst
Author-email: oliver.k.ernst@gmail.com
License: UNKNOWN
Platform: UNKNOWN
Requires-Python: >=3.7
License-File: LICENSE
